AUTHORS.rst
CHANGES.rst
LICENSE.txt
MANIFEST.in
README.rst
TODO.rst
setup.py
django_icanhaz.egg-info/PKG-INFO
django_icanhaz.egg-info/SOURCES.txt
django_icanhaz.egg-info/dependency_links.txt
django_icanhaz.egg-info/not-zip-safe
django_icanhaz.egg-info/top_level.txt
icanhaz/__init__.py
icanhaz/conf.py
icanhaz/finders.py
icanhaz/loading.py
icanhaz/models.py
icanhaz/templatetags/__init__.py
icanhaz/templatetags/icanhaz.py
icanhaz/tests/__init__.py
icanhaz/tests/mockfinders.py
icanhaz/tests/test_finders.py
icanhaz/tests/test_loading.py
icanhaz/tests/test_ttag.py
icanhaz/tests/utils.py